AYABInterface/__init__.py
AYABInterface/actions.py
AYABInterface/carriages.py
AYABInterface/interaction.py
AYABInterface/machines.py
AYABInterface/needle_positions.py
AYABInterface/serial.py
AYABInterface/utils.py
AYABInterface/communication/__init__.py
AYABInterface/communication/cache.py
AYABInterface/communication/carriages.py
AYABInterface/communication/hardware_messages.py
AYABInterface/communication/host_messages.py
AYABInterface/communication/states.py
AYABInterface/communication/test/conftest.py
AYABInterface/communication/test/test_assertions.py
AYABInterface/communication/test/test_carriages.py
AYABInterface/communication/test/test_communication_integration.py
AYABInterface/communication/test/test_communication_mocked.py
AYABInterface/communication/test/test_hardware_messages.py
AYABInterface/communication/test/test_host_messages.py
AYABInterface/communication/test/test_needle_position_cache.py
AYABInterface/communication/test/test_state_machine.py
AYABInterface/convert/__init__.py
AYABInterface/convert/test/conftest.py
AYABInterface/convert/test/test_colors_to_needle_positions.py
AYABInterface/convert/test/test_knitting_pattern_to_colors.py
AYABInterface/test/conftest.py
AYABInterface/test/test_actions.py
AYABInterface/test/test_import.py
AYABInterface/test/test_interaction.py
AYABInterface/test/test_machines.py
AYABInterface/test/test_needle_positions.py
AYABInterface/test/test_serial.py
AYABInterface/test/test_utils.py
AYABInterface/test/test_patterns/block4x4-colored.json
AYABInterface/test/test_patterns/block4x4.json
AYABInterface/test/test_patterns/block6x3.json
AYABInterface-0.0.9.dist-info/DESCRIPTION.rst
AYABInterface-0.0.9.dist-info/METADATA
AYABInterface-0.0.9.dist-info/RECORD
AYABInterface-0.0.9.dist-info/WHEEL
AYABInterface-0.0.9.dist-info/metadata.json
AYABInterface-0.0.9.dist-info/top_level.txt
