Metadata-Version: 2.0
Name: AYABInterface
Version: 0.0.9
Summary: A Python library with the interface to the AYAB shield.
Home-page: https://github.com/fossasia/AYABInterface
Author: Nicco Kunzmann
Author-email: niccokunzmann@rambler.ru
License: LGPL
Keywords: knitting ayab fashion
Platform: UNKNOWN
Classifier: Intended Audience :: Developers
Classifier: License :: OSI Approved :: GNU Lesser General Public License v3 (LGPLv3)
Classifier: Topic :: Software Development :: Libraries :: Python Modules
Classifier: Topic :: Artistic Software
Classifier: Topic :: Home Automation
Classifier: Topic :: Utilities
Classifier: Intended Audience :: Manufacturing
Classifier: Natural Language :: English
Classifier: Operating System :: OS Independent
Classifier: Programming Language :: Python :: 3 :: Only
Classifier: Development Status :: 5 - Production/Stable
Requires-Dist: crc8 (==0.0.3)
Requires-Dist: pyserial (==3.1.1)
